MANIFEST.in
README.rst
requirements.txt
setup.py
flaskinit/__init__.py
flaskinit/main.py
flaskinit/metadata.py
flaskinit.egg-info/PKG-INFO
flaskinit.egg-info/SOURCES.txt
flaskinit.egg-info/dependency_links.txt
flaskinit.egg-info/entry_points.txt
flaskinit.egg-info/not-zip-safe
flaskinit.egg-info/requires.txt
flaskinit.egg-info/top_level.txt
flaskinit/templates/app.py
flaskinit/templates/blueprint.py
flaskinit/templates/extensions.py
flaskinit/templates/requirements.txt
flaskinit/templates/runserver.py
flaskinit/templates/views.py
flaskinit/templates/wsgi.py
flaskinit/templates/extensions/sqlalchemy.py