Metadata-Version: 1.0
Name: flaskinit
Version: 0.0.1
Summary: Bootstraps Flask projects
Home-page: https://github.com/marksteve/flaskinit
Author: Mark Steve Samson
Author-email: hello@marksteve.com
License: MIT
Platform: UNKNOWN
